pyjet/VERSION.txt
pyjet/__init__.py
pyjet/_libpyjet.cpython-39-darwin.so
pyjet/_version.py
pyjet/utils.py
pyjet/src/2to3.h
pyjet/src/_libpyjet.cpp
pyjet/src/_libpyjet.pyx
pyjet/src/fastjet.h
pyjet/src/fastjet.pxd
pyjet/src/fjcore.cpp
pyjet/src/fjcore.h
pyjet/testdata/__init__.py
pyjet/testdata/single-event.dat
pyjet-1.9.0.dist-info/COPYING
pyjet-1.9.0.dist-info/METADATA
pyjet-1.9.0.dist-info/WHEEL
pyjet-1.9.0.dist-info/top_level.txt
pyjet-1.9.0.dist-info/RECORD
