Metadata-Version: 2.1
Name: pyjet
Version: 1.9.0
Summary: The interface between FastJet and NumPy
Home-page: https://github.com/scikit-hep/pyjet
Author: Noel Dawe
Author-email: noel@dawe.me
Maintainer: The Scikit-HEP admins
Maintainer-email: scikit-hep-admins@googlegroups.com
License: GPLv3
Classifier: Intended Audience :: Science/Research
Classifier: Intended Audience :: Developers
Classifier: Topic :: Software Development
Classifier: Topic :: Scientific/Engineering
Classifier: Operating System :: Unix
Classifier: Operating System :: MacOS
Classifier: Operating System :: Microsoft :: Windows
Classifier: License :: OSI Approved :: GNU General Public License v3 (GPLv3)
Classifier: Programming Language :: Python
Classifier: Programming Language :: Python :: 3 :: Only
Classifier: Programming Language :: Python :: 3.7
Classifier: Programming Language :: Python :: 3.8
Classifier: Programming Language :: Python :: 3.9
Classifier: Programming Language :: Python :: 3.10
Classifier: Programming Language :: Python :: Implementation :: PyPy
Classifier: Programming Language :: Python :: Implementation :: CPython
Classifier: Programming Language :: C++
Classifier: Programming Language :: Cython
Classifier: Development Status :: 7 - Inactive
Requires-Python: >=3.7
Provides-Extra: dev
Provides-Extra: test
Provides-Extra: all
License-File: COPYING
